fifty/__init__.py
fifty/cli.py
fifty/commands/__init__.py
fifty/commands/train.py
fifty/commands/whatis.py
fifty/utilities/__init__.py
fifty/utilities/framework.py
fifty/utilities/labels.json
fifty/utilities/models/4096_1.h5
fifty/utilities/models/4096_1_lighter.h5
fifty/utilities/models/4096_2.h5
fifty/utilities/models/4096_3.h5
fifty/utilities/models/4096_4.h5
fifty/utilities/models/4096_5.h5
fifty/utilities/models/4096_6.h5
fifty/utilities/models/512_1.h5
fifty/utilities/models/512_2.h5
fifty/utilities/models/512_3.h5
fifty/utilities/models/512_4.h5
fifty/utilities/models/512_5.h5
fifty/utilities/models/512_6.h5
fifty/utilities/models/__init__.py
fifty-1.0.0.dist-info/DESCRIPTION.rst
fifty-1.0.0.dist-info/METADATA
fifty-1.0.0.dist-info/RECORD
fifty-1.0.0.dist-info/WHEEL
fifty-1.0.0.dist-info/entry_points.txt
fifty-1.0.0.dist-info/metadata.json
fifty-1.0.0.dist-info/top_level.txt
